reahl/component/__init__.py
reahl/component/config.py
reahl/component/context.py
reahl/component/dbutils.py
reahl/component/decorators.py
reahl/component/eggs.py
reahl/component/exceptions.py
reahl/component/i18n.py
reahl/component/migration.py
reahl/component/modelinterface.py
reahl/component/shelltools.py
reahl/component_dev/__init__.py
reahl/component_dev/action.puml
reahl/component_dev/contents.mm
reahl/component_dev/database_components.puml
reahl/component_dev/egg_component_metadata.puml
reahl/component_dev/events.puml
reahl/component_dev/fields_and_events_overview.puml
reahl/component_dev/fields_and_field_metadata.puml
reahl/component_dev/reahl_commandline_shells.puml
reahl/component_dev/schema_migration.puml
reahl/component_dev/test_argumentchecks.py
reahl/component_dev/test_component.py
reahl/component_dev/test_config.py
reahl/component_dev/test_context.py
reahl/component_dev/test_dbutils.py
reahl/component_dev/test_decorators.py
reahl/component_dev/test_domainaccesscontrol.py
reahl/component_dev/test_field.py
reahl/component_dev/test_i18n.py
reahl/component_dev/test_migration.py
reahl/messages/reahl-component
reahl/messages/af/LC_MESSAGES/reahl-component.mo
reahl/messages/af/LC_MESSAGES/reahl-component.po
reahl_component-7.0.3.dist-info/COPYING
reahl_component-7.0.3.dist-info/LICENSE
reahl_component-7.0.3.dist-info/METADATA
reahl_component-7.0.3.dist-info/WHEEL
reahl_component-7.0.3.dist-info/entry_points.txt
reahl_component-7.0.3.dist-info/reahl-component.toml
reahl_component-7.0.3.dist-info/top_level.txt
reahl_component-7.0.3.dist-info/RECORD
